{
  "$schema": "https://schema.management.azure.com/schemas/2019-04-01/deploymentTemplate.json#",
  "contentVersion": "1.0.0.0",
  "parameters": {
    "vmName": {
      "type": "string",
      "metadata": {
        "description": "Name of the VM."
      }
    },
    "vmSize": {
      "type": "string",
      "defaultValue": "Standard_B4ms",
      "metadata": {
        "description": "Size of the VM."
      }
    },
    "vmImageResourceId": {
      "type": "string",
      "metadata": {
        "description": "Image to build VM Id."
      }
    },
    "adminUserName": {
      "type": "string",
      "metadata": {
        "description": "Virtual Machine Admin Username"
      }
    },
    "adminPassword": {
      "type": "string",
      "metadata": {
        "description": "Virtual Machine Password"
      }
    },
    "virtualNetworkId": {
      "type": "string",
      "defaultValue": "",
      "metadata": {
        "description": "Name of the virtual network"
      }
    },
    "subnetName": {
      "type": "string",
      "defaultValue": "default",
      "metadata": {
        "description": "Name of the subnet"
      }
    },
    "subnetIpPrefix": {
      "type": "string",
      "defaultValue": "",
      "metadata": {
        "description": "IP address prefix for the subnet"
      }
    }
  },
  "variables": {
    "networkInterfaceName": "[concat(parameters('vmName'), '-nic')]",
    "publicIPAddressName": "[concat(parameters('vmName'), '-ip')]",
    "virtualNetworkName": "[concat(parameters('vmName'), '-vnet')]",
    "networkSecurityGroupName": "[concat(parameters('vmName'), '-nsg')]"
  },
  "resources": [
    {
      "condition": "[equals(parameters('virtualNetworkId'), '')]",
      "type": "Microsoft.Network/virtualNetworks",
      "apiVersion": "2020-11-01",
      "name": "[variables('virtualNetworkName')]",
      "location": "[resourceGroup().location]",
      "properties": {
        "addressSpace": {
          "addressPrefixes": [
            "[parameters('subnetIpPrefix')]"
          ]
        },
        "subnets": [
          {
            "name": "[parameters('subnetName')]",
            "properties": {
              "addressPrefix": "[parameters('subnetIpPrefix')]",
              "delegations": [],
              "privateEndpointNetworkPolicies": "Disabled",
              "privateLinkServiceNetworkPolicies": "Disabled"
            }
          }
        ],
        "virtualNetworkPeerings": [],
        "enableDdosProtection": false
      }
    },
    {
      "type": "Microsoft.Compute/virtualMachines",
      "apiVersion": "2020-12-01",
      "name": "[parameters('vmName')]",
      "location": "[resourceGroup().location]",
      "dependsOn": [
        "[resourceId('Microsoft.Network/networkInterfaces/', variables('networkInterfaceName'))]"
      ],
      "properties": {
        "hardwareProfile": {
          "vmSize": "[parameters('vmSize')]"
        },
        "storageProfile": {
          "osDisk": {
            "createOption": "FromImage",
            "name": "[concat(parameters('vmName'), '-disk')]",
            "caching": "ReadWrite",
            "managedDisk": {
              "storageAccountType": "Standard_LRS"
            }
          },
          "imageReference": {
            "id": "[parameters('VmImageResourceId')]"
          }
        },
        "osProfile": {
          "adminUsername": "[parameters('adminUsername')]",
          "computerName": "SailWebsite",
          "adminPassword": "[parameters('adminPassword')]"
        },
        "networkProfile": {
          "networkInterfaces": [
            {
              "id": "[resourceId('Microsoft.Network/networkInterfaces', variables('networkInterfaceName'))]"
            }
          ]
        }
      }
    }
  ]
}
